kimvv/__init__.py
kimvv/core.py
kimvv/CrystalStructureAndEnergyVsPressure/__init__.py
kimvv/CrystalStructureAndEnergyVsPressure/kimspec.edn
kimvv/CrystalStructureAndEnergyVsPressure/requirements.txt
kimvv/CrystalStructureAndEnergyVsPressure/test_driver/__init__.py
kimvv/CrystalStructureAndEnergyVsPressure/test_driver/test_driver.py
kimvv/ElasticConstantsCrystal/__init__.py
kimvv/ElasticConstantsCrystal/kimspec.edn
kimvv/ElasticConstantsCrystal/requirements.txt
kimvv/ElasticConstantsCrystal/test_driver/__init__.py
kimvv/ElasticConstantsCrystal/test_driver/elastic.py
kimvv/ElasticConstantsCrystal/test_driver/test_driver.py
kimvv/EquilibriumCrystalStructure/__init__.py
kimvv/EquilibriumCrystalStructure/kimspec.edn
kimvv/EquilibriumCrystalStructure/requirements.txt
kimvv/EquilibriumCrystalStructure/test_driver/__init__.py
kimvv/EquilibriumCrystalStructure/test_driver/test_driver.py
kimvv/GroundStateCrystalStructure/__init__.py
kimvv/GroundStateCrystalStructure/kimspec.edn
kimvv/GroundStateCrystalStructure/requirements.txt
kimvv/GroundStateCrystalStructure/test_driver/__init__.py
kimvv/GroundStateCrystalStructure/test_driver/reference_map.py
kimvv/GroundStateCrystalStructure/test_driver/test_driver.py
kimvv/VacancyFormationEnergyRelaxationVolumeCrystal/__init__.py
kimvv/VacancyFormationEnergyRelaxationVolumeCrystal/kimspec.edn
kimvv/VacancyFormationEnergyRelaxationVolumeCrystal/requirements.txt
kimvv/VacancyFormationEnergyRelaxationVolumeCrystal/test_driver/__init__.py
kimvv/VacancyFormationEnergyRelaxationVolumeCrystal/test_driver/test_driver.py
kimvv-0.1.10.dist-info/licenses/LICENSE
kimvv-0.1.10.dist-info/METADATA
kimvv-0.1.10.dist-info/WHEEL
kimvv-0.1.10.dist-info/top_level.txt
kimvv-0.1.10.dist-info/RECORD
