Metadata-Version: 2.4
Name: kimvv
Version: 0.1.10
Summary: OpenKIM material property computations for arbitrary crystal structures as Python classes
Author: ilia Nikiforov <nikif002@umn.edu>, Eric Fuemmeler <efuemmel@umn.edu>, Ellad Tadmor, Junhao Li
Maintainer-email: ilia Nikiforov <nikif002@umn.edu>
Project-URL: Homepage, https://github.com/openkim/kimvv
Project-URL: Issues, https://github.com/openkim/kimvv/issues
Keywords: interatomic potential,openkim,crystal genome
Classifier: Development Status :: 4 - Beta
Classifier: License :: OSI Approved :: Common Development and Distribution License 1.0 (CDDL-1.0)
Classifier: Programming Language :: Python :: 3
Classifier: Operating System :: OS Independent
Classifier: Topic :: Scientific/Engineering :: Physics
Requires-Python: >=3.8
License-File: LICENSE
Requires-Dist: kim_edn
Requires-Dist: kim_property>=2.6.11
Requires-Dist: kim_tools>=0.4.3
Requires-Dist: kim-tools>=0.3.5
Requires-Dist: numpy
Requires-Dist: kim-tools>=0.3.7
Requires-Dist: numdifftools
Requires-Dist: numpy
Requires-Dist: ase
Requires-Dist: kim-tools>=0.3.10
Requires-Dist: matplotlib
Requires-Dist: kim-tools
Requires-Dist: ase
Requires-Dist: kim-tools
Requires-Dist: numpy
Requires-Dist: scipy
Requires-Dist: ase
Dynamic: license-file
